{
  "model": "teg_gnn",
  "split": "B",
  "seed": 2,
  "epochs": 50,
  "experiment_tag": "teg_ce_ord",
  "alpha_ord": 0.5,
  "alpha_hr": 0.0,
  "alpha_topk": 0.0,
  "topk_frac": 0.2,
  "stage1_epochs": 0,
  "pos_weight": 5.0,
  "history": [
    {
      "epoch": 1,
      "loss": 5.854424476623535
    },
    {
      "epoch": 2,
      "loss": 5.66021728515625
    },
    {
      "epoch": 3,
      "loss": 5.520326614379883
    },
    {
      "epoch": 4,
      "loss": 5.315762996673584
    },
    {
      "epoch": 5,
      "loss": 5.238199234008789
    },
    {
      "epoch": 6,
      "loss": 5.1083807945251465
    },
    {
      "epoch": 7,
      "loss": 5.004254341125488
    },
    {
      "epoch": 8,
      "loss": 4.943266868591309
    },
    {
      "epoch": 9,
      "loss": 4.807009220123291
    },
    {
      "epoch": 10,
      "loss": 4.710935115814209
    },
    {
      "epoch": 11,
      "loss": 4.62811279296875
    },
    {
      "epoch": 12,
      "loss": 4.538649082183838
    },
    {
      "epoch": 13,
      "loss": 4.492524147033691
    },
    {
      "epoch": 14,
      "loss": 4.4361371994018555
    },
    {
      "epoch": 15,
      "loss": 4.309983253479004
    },
    {
      "epoch": 16,
      "loss": 4.219810485839844
    },
    {
      "epoch": 17,
      "loss": 4.201201438903809
    },
    {
      "epoch": 18,
      "loss": 4.105216979980469
    },
    {
      "epoch": 19,
      "loss": 4.011099815368652
    },
    {
      "epoch": 20,
      "loss": 3.9101696014404297
    },
    {
      "epoch": 21,
      "loss": 3.8795719146728516
    },
    {
      "epoch": 22,
      "loss": 3.800724506378174
    },
    {
      "epoch": 23,
      "loss": 3.730093002319336
    },
    {
      "epoch": 24,
      "loss": 3.6895108222961426
    },
    {
      "epoch": 25,
      "loss": 3.6285791397094727
    },
    {
      "epoch": 26,
      "loss": 3.5519819259643555
    },
    {
      "epoch": 27,
      "loss": 3.5578534603118896
    },
    {
      "epoch": 28,
      "loss": 3.4951698780059814
    },
    {
      "epoch": 29,
      "loss": 3.4414968490600586
    },
    {
      "epoch": 30,
      "loss": 3.3250484466552734
    },
    {
      "epoch": 31,
      "loss": 3.3301150798797607
    },
    {
      "epoch": 32,
      "loss": 3.3110852241516113
    },
    {
      "epoch": 33,
      "loss": 3.262023448944092
    },
    {
      "epoch": 34,
      "loss": 3.181226968765259
    },
    {
      "epoch": 35,
      "loss": 3.1427557468414307
    },
    {
      "epoch": 36,
      "loss": 3.041367530822754
    },
    {
      "epoch": 37,
      "loss": 3.067060947418213
    },
    {
      "epoch": 38,
      "loss": 3.0041966438293457
    },
    {
      "epoch": 39,
      "loss": 2.987152099609375
    },
    {
      "epoch": 40,
      "loss": 2.9363131523132324
    },
    {
      "epoch": 41,
      "loss": 2.8995747566223145
    },
    {
      "epoch": 42,
      "loss": 2.8582260608673096
    },
    {
      "epoch": 43,
      "loss": 2.8604705333709717
    },
    {
      "epoch": 44,
      "loss": 2.7633986473083496
    },
    {
      "epoch": 45,
      "loss": 2.769831657409668
    },
    {
      "epoch": 46,
      "loss": 2.7610926628112793
    },
    {
      "epoch": 47,
      "loss": 2.676631450653076
    },
    {
      "epoch": 48,
      "loss": 2.6606698036193848
    },
    {
      "epoch": 49,
      "loss": 2.641761302947998
    },
    {
      "epoch": 50,
      "loss": 2.582239866256714
    }
  ],
  "metrics": {
    "data_2020_train": {
      "macro_f1": 0.43053560282289566,
      "weighted_f1": 0.6816031100124433,
      "mae": 1.169486139703747,
      "qwk": 0.4442766389593994,
      "recall_6_8": 0.4,
      "precision_6_8": 0.64,
      "pr_auc_high": 0.5954345359051988,
      "high_fn_rate": 0.6
    },
    "data_2021_train": {
      "macro_f1": 0.5826094688486205,
      "weighted_f1": 0.7315258434010492,
      "mae": 1.066921826386972,
      "qwk": 0.5689104595267169,
      "recall_6_8": 0.44,
      "precision_6_8": 0.7857142857142857,
      "pr_auc_high": 0.72414796158821,
      "high_fn_rate": 0.56
    },
    "data_2021_test": {
      "macro_f1": 0.26511153477748306,
      "weighted_f1": 0.5890569780655988,
      "mae": 1.461664277430427,
      "qwk": 0.2696357298947103,
      "recall_6_8": 0.23076923076923078,
      "precision_6_8": 0.4,
      "pr_auc_high": 0.3531230705994546,
      "high_fn_rate": 0.7692307692307693
    }
  },
  "split_sizes": {
    "data_2020": {
      "train": 419,
      "val": 0,
      "test": 0
    },
    "data_2021": {
      "train": 221,
      "val": 0,
      "test": 222
    }
  }
}